apytizer/__init__.py
apytizer/abstracts/__init__.py
apytizer/abstracts/api.py
apytizer/abstracts/endpoint.py
apytizer/abstracts/model.py
apytizer/abstracts/session.py
apytizer/adapters/__init__.py
apytizer/adapters/transport.py
apytizer/base/__init__.py
apytizer/base/api.py
apytizer/base/endpoint.py
apytizer/base/model.py
apytizer/decorators/__init__.py
apytizer/decorators/caching.py
apytizer/decorators/connection.py
apytizer/decorators/json.py
apytizer/decorators/pagination.py
apytizer/utils/__init__.py
apytizer/utils/generate_key.py
apytizer/utils/merge.py
apytizer-0.0.1a0.dist-info/LICENSE
apytizer-0.0.1a0.dist-info/METADATA
apytizer-0.0.1a0.dist-info/WHEEL
apytizer-0.0.1a0.dist-info/top_level.txt
apytizer-0.0.1a0.dist-info/RECORD
